{
	"info": {
		"_postman_id": "1eeea9ad-f7bf-4fef-b0bc-4ea64350bca6",
		"name": "New Collection",
		"schema": "https://schema.getpostman.com/json/collection/v2.1.0/collection.json"
	},
	"item": [
		{
			"name": "Get Students",
			"protocolProfileBehavior": {
				"disableBodyPruning": true
			},
			"request": {
				"method": "GET",
				"header": [],
				"body": {
					"mode": "raw",
					"raw": "{\r\n    \"projectMemberId\": 1\r\n}",
					"options": {
						"raw": {
							"language": "json"
						}
					}
				},
				"url": {
					"raw": "http://localhost:8081/api/students",
					"protocol": "http",
					"host": [
						"localhost"
					],
					"port": "8081",
					"path": [
						"api",
						"students"
					]
				}
			},
			"response": []
		},
		{
			"name": "Get Student",
			"request": {
				"method": "GET",
				"header": [],
				"url": {
					"raw": "http://localhost:8081/api/students/1",
					"protocol": "http",
					"host": [
						"localhost"
					],
					"port": "8081",
					"path": [
						"api",
						"students",
						"1"
					]
				}
			},
			"response": []
		},
		{
			"name": "Add Student",
			"request": {
				"method": "POST",
				"header": [],
				"body": {
					"mode": "raw",
					"raw": "{\r\n    \"id\": 2,\r\n    \"firstName\": \"Popescu\",\r\n    \"lastName\": \"Andrei-Cristian\",\r\n    \"email\": \"popescuandrei@gmail.com\"\r\n}",
					"options": {
						"raw": {
							"language": "json"
						}
					}
				},
				"url": {
					"raw": "http://localhost:8081/api/students",
					"protocol": "http",
					"host": [
						"localhost"
					],
					"port": "8081",
					"path": [
						"api",
						"students"
					]
				}
			},
			"response": []
		},
		{
			"name": "Delete Student",
			"request": {
				"method": "DELETE",
				"header": [],
				"url": {
					"raw": "http://localhost:8081/api/students/2",
					"protocol": "http",
					"host": [
						"localhost"
					],
					"port": "8081",
					"path": [
						"api",
						"students",
						"2"
					]
				}
			},
			"response": []
		},
		{
			"name": "Delete Students",
			"request": {
				"method": "DELETE",
				"header": [],
				"url": {
					"raw": "http://localhost:8081/api/students",
					"protocol": "http",
					"host": [
						"localhost"
					],
					"port": "8081",
					"path": [
						"api",
						"students"
					]
				}
			},
			"response": []
		},
		{
			"name": "Get Projects",
			"request": {
				"method": "GET",
				"header": [],
				"url": {
					"raw": "http://localhost:8081/api/projects",
					"protocol": "http",
					"host": [
						"localhost"
					],
					"port": "8081",
					"path": [
						"api",
						"projects"
					]
				}
			},
			"response": []
		},
		{
			"name": "Get Project",
			"request": {
				"method": "GET",
				"header": [],
				"url": {
					"raw": "http://localhost:8081/api/projects/1",
					"protocol": "http",
					"host": [
						"localhost"
					],
					"port": "8081",
					"path": [
						"api",
						"projects",
						"1"
					]
				}
			},
			"response": []
		},
		{
			"name": "Add Project",
			"request": {
				"method": "POST",
				"header": [],
				"body": {
					"mode": "raw",
					"raw": "{\r\n    \"id\": 2,\r\n    \"title\": \"Project 2\",\r\n    \"description\": \"test\"\r\n}",
					"options": {
						"raw": {
							"language": "json"
						}
					}
				},
				"url": {
					"raw": "http://localhost:8081/api/projects",
					"protocol": "http",
					"host": [
						"localhost"
					],
					"port": "8081",
					"path": [
						"api",
						"projects"
					]
				}
			},
			"response": []
		},
		{
			"name": "Delete Project",
			"request": {
				"method": "DELETE",
				"header": [],
				"url": {
					"raw": "http://localhost:8081/api/projects/1",
					"protocol": "http",
					"host": [
						"localhost"
					],
					"port": "8081",
					"path": [
						"api",
						"projects",
						"1"
					]
				}
			},
			"response": []
		},
		{
			"name": "Delete Projects",
			"request": {
				"method": "DELETE",
				"header": [],
				"url": {
					"raw": "http://localhost:8081/api/projects",
					"protocol": "http",
					"host": [
						"localhost"
					],
					"port": "8081",
					"path": [
						"api",
						"projects"
					]
				}
			},
			"response": []
		},
		{
			"name": "Get Deliverables",
			"request": {
				"method": "GET",
				"header": [],
				"url": {
					"raw": "http://localhost:8081/api/deliverables",
					"protocol": "http",
					"host": [
						"localhost"
					],
					"port": "8081",
					"path": [
						"api",
						"deliverables"
					]
				}
			},
			"response": []
		},
		{
			"name": "Get Deliverable",
			"request": {
				"method": "GET",
				"header": [],
				"url": {
					"raw": "http://localhost:8081/api/deliverables/1",
					"protocol": "http",
					"host": [
						"localhost"
					],
					"port": "8081",
					"path": [
						"api",
						"deliverables",
						"1"
					]
				}
			},
			"response": []
		},
		{
			"name": "Add deliverable",
			"request": {
				"method": "POST",
				"header": [],
				"body": {
					"mode": "raw",
					"raw": "{\r\n    \"id\": 1,\r\n    \"title\": \"Phase 1\",\r\n    \"description\": \"asd\",\r\n    \"end\": \"10-12-2021\",\r\n    \"deliverableId\": 1\r\n}",
					"options": {
						"raw": {
							"language": "json"
						}
					}
				},
				"url": {
					"raw": "http://localhost:8081/api/deliverables",
					"protocol": "http",
					"host": [
						"localhost"
					],
					"port": "8081",
					"path": [
						"api",
						"deliverables"
					]
				}
			},
			"response": []
		},
		{
			"name": "Put Deliverable",
			"request": {
				"method": "PUT",
				"header": [],
				"body": {
					"mode": "raw",
					"raw": "{\r\n    \"link\": \"https://www.google.com\"\r\n}",
					"options": {
						"raw": {
							"language": "json"
						}
					}
				},
				"url": {
					"raw": "http://localhost:8081/api/deliverables/1",
					"protocol": "http",
					"host": [
						"localhost"
					],
					"port": "8081",
					"path": [
						"api",
						"deliverables",
						"1"
					]
				}
			},
			"response": []
		},
		{
			"name": "Delete Deliverable",
			"request": {
				"method": "DELETE",
				"header": [],
				"url": {
					"raw": "http://localhost:8081/api/deliverables/1",
					"protocol": "http",
					"host": [
						"localhost"
					],
					"port": "8081",
					"path": [
						"api",
						"deliverables",
						"1"
					]
				}
			},
			"response": []
		},
		{
			"name": "Delete Deliverables",
			"request": {
				"method": "DELETE",
				"header": [],
				"url": {
					"raw": "http://localhost:8081/api/deliverables",
					"protocol": "http",
					"host": [
						"localhost"
					],
					"port": "8081",
					"path": [
						"api",
						"deliverables"
					]
				}
			},
			"response": []
		},
		{
			"name": "Get Professors",
			"request": {
				"method": "GET",
				"header": [],
				"url": {
					"raw": "http://localhost:8081/api/professors",
					"protocol": "http",
					"host": [
						"localhost"
					],
					"port": "8081",
					"path": [
						"api",
						"professors"
					]
				}
			},
			"response": []
		},
		{
			"name": "Get Professor",
			"request": {
				"method": "GET",
				"header": [],
				"url": {
					"raw": "http://localhost:8081/api/professors/1",
					"protocol": "http",
					"host": [
						"localhost"
					],
					"port": "8081",
					"path": [
						"api",
						"professors",
						"1"
					]
				}
			},
			"response": []
		},
		{
			"name": "Add professor",
			"request": {
				"method": "POST",
				"header": [],
				"body": {
					"mode": "raw",
					"raw": "{\r\n     \"id\": 1,\r\n     \"firstName\": \"Georgescu\",\r\n     \"lastName\": \"Andrei\",\r\n     \"email\": \"georgescuandrei@gmail.com\"\r\n}",
					"options": {
						"raw": {
							"language": "json"
						}
					}
				},
				"url": {
					"raw": "http://localhost:8081/api/professors",
					"protocol": "http",
					"host": [
						"localhost"
					],
					"port": "8081",
					"path": [
						"api",
						"professors"
					]
				}
			},
			"response": []
		},
		{
			"name": "Delete professor",
			"request": {
				"method": "DELETE",
				"header": [],
				"url": {
					"raw": "http://localhost:8081/api/professors/1",
					"protocol": "http",
					"host": [
						"localhost"
					],
					"port": "8081",
					"path": [
						"api",
						"professors",
						"1"
					]
				}
			},
			"response": []
		},
		{
			"name": "Delete Professors",
			"request": {
				"method": "DELETE",
				"header": [],
				"url": {
					"raw": "http://localhost:8081/api/professors",
					"protocol": "http",
					"host": [
						"localhost"
					],
					"port": "8081",
					"path": [
						"api",
						"professors"
					]
				}
			},
			"response": []
		},
		{
			"name": "Get Evaluators",
			"request": {
				"method": "GET",
				"header": [],
				"url": {
					"raw": "http://localhost:8081/api/projectEvaluators",
					"protocol": "http",
					"host": [
						"localhost"
					],
					"port": "8081",
					"path": [
						"api",
						"projectEvaluators"
					]
				}
			},
			"response": []
		},
		{
			"name": "Get Evaluator",
			"request": {
				"method": "GET",
				"header": [],
				"url": {
					"raw": "http://localhost:8081/api/projectEvaluators/1",
					"protocol": "http",
					"host": [
						"localhost"
					],
					"port": "8081",
					"path": [
						"api",
						"projectEvaluators",
						"1"
					]
				}
			},
			"response": []
		},
		{
			"name": "Add Evaluator",
			"request": {
				"method": "POST",
				"header": [],
				"body": {
					"mode": "raw",
					"raw": "{\r\n    \"projectId\": 1,\r\n    \"studentId\": 2\r\n}",
					"options": {
						"raw": {
							"language": "json"
						}
					}
				},
				"url": {
					"raw": "http://localhost:8081/api/projectEvaluators",
					"protocol": "http",
					"host": [
						"localhost"
					],
					"port": "8081",
					"path": [
						"api",
						"projectEvaluators"
					]
				}
			},
			"response": []
		},
		{
			"name": "Put Evaluator",
			"request": {
				"method": "PUT",
				"header": [],
				"body": {
					"mode": "raw",
					"raw": "{\r\n    \"grade\": 5.2\r\n}",
					"options": {
						"raw": {
							"language": "json"
						}
					}
				},
				"url": {
					"raw": "http://localhost:8081/api/projectEvaluators/1",
					"protocol": "http",
					"host": [
						"localhost"
					],
					"port": "8081",
					"path": [
						"api",
						"projectEvaluators",
						"1"
					]
				}
			},
			"response": []
		},
		{
			"name": "Delete Evaluator",
			"request": {
				"method": "DELETE",
				"header": [],
				"url": {
					"raw": "http://localhost:8081/api/projectEvaluators/1",
					"protocol": "http",
					"host": [
						"localhost"
					],
					"port": "8081",
					"path": [
						"api",
						"projectEvaluators",
						"1"
					]
				}
			},
			"response": []
		},
		{
			"name": "Delete Evaluators",
			"request": {
				"method": "DELETE",
				"header": [],
				"url": {
					"raw": "http://localhost:8081/api/projectEvaluators",
					"protocol": "http",
					"host": [
						"localhost"
					],
					"port": "8081",
					"path": [
						"api",
						"projectEvaluators"
					]
				}
			},
			"response": []
		},
		{
			"name": "AuthenticateStudent",
			"protocolProfileBehavior": {
				"disableBodyPruning": true
			},
			"request": {
				"method": "GET",
				"header": [],
				"body": {
					"mode": "raw",
					"raw": "{\r\n    \"id\": \"1\"\r\n}",
					"options": {
						"raw": {
							"language": "json"
						}
					}
				},
				"url": {
					"raw": "http://localhost:8081/api/authenticateStudent/ionescu.leoanrd28@gmail.com/password1",
					"protocol": "http",
					"host": [
						"localhost"
					],
					"port": "8081",
					"path": [
						"api",
						"authenticateStudent",
						"ionescu.leoanrd28@gmail.com",
						"password1"
					]
				}
			},
			"response": []
		},
		{
			"name": "AuthenticateProfessor",
			"request": {
				"method": "GET",
				"header": [],
				"url": null
			},
			"response": []
		}
	]
}